virtex.py
virtex-0.1.1.dist-info/METADATA
virtex-0.1.1.dist-info/WHEEL
virtex-0.1.1.dist-info/top_level.txt
virtex-0.1.1.dist-info/RECORD
