Metadata-Version: 2.1
Name: virtex
Version: 0.1.1
Summary: Virtex API wrapper
Requires-Python: >=3.12
Requires-Dist: pandas>=2.2.3
Requires-Dist: python-dotenv>=1.0.1
Requires-Dist: requests>=2.32.3
Requires-Dist: websocket-client>=1.8.0
